LICENSE
README.md
setup.cfg
setup.py
src/benchling_wrapper/__init__.py
src/benchling_wrapper/benchling_wrapper.py
src/benchling_wrapper.egg-info/PKG-INFO
src/benchling_wrapper.egg-info/SOURCES.txt
src/benchling_wrapper.egg-info/dependency_links.txt
src/benchling_wrapper.egg-info/requires.txt
src/benchling_wrapper.egg-info/top_level.txt