Metadata-Version: 2.1
Name: benchling-wrapper
Version: 0.4.0
Summary: To make integrations with Benchling easier we prepared a wrapper with the most used API functions.
Home-page: https://bitbucket.org/egor-yatsishin/benchling-wrapper
Author: Ivan Ivanov
Author-email: 300899@gmail.com
License: MIT
Keywords: benchling wrapper
Classifier: Development Status :: 3 - Alpha
Classifier: Intended Audience :: Developers
Classifier: Topic :: Software Development :: Libraries :: Python Modules
Classifier: License :: OSI Approved :: MIT License
Classifier: Programming Language :: Python :: 3
Classifier: Programming Language :: Python :: 3.10
Classifier: Programming Language :: Python :: 3.11
Requires-Python: >=3.10
License-File: LICENSE
